Metadata-Version: 1.1
Name: emojins
Version: 0.0.7
Summary: this is a package that addes emoji to text.
Home-page: UNKNOWN
Author: Ibuki Yoshida
Author-email: ibuki042004@gmail.com
License: MIT
Platform: UNKNOWN
Classifier: Development Status :: 5 - Production/Stable
Classifier: Intended Audience :: Education
Classifier: Operating System :: MacOS :: MacOS X
Classifier: License :: OSI Approved :: MIT License
Classifier: Programming Language :: Python :: 3
